mcp_server_weather_cuhksz/__init__.py
mcp_server_weather_cuhksz/__main__.py
mcp_server_weather_cuhksz/mcp_weather.py
mcp_server_weather_cuhksz-0.2.6.dist-info/licenses/LICENSE
mcp_server_weather_cuhksz-0.2.6.dist-info/METADATA
mcp_server_weather_cuhksz-0.2.6.dist-info/WHEEL
mcp_server_weather_cuhksz-0.2.6.dist-info/entry_points.txt
mcp_server_weather_cuhksz-0.2.6.dist-info/top_level.txt
mcp_server_weather_cuhksz-0.2.6.dist-info/RECORD
