Metadata-Version: 2.4
Name: mcp-server-weather-cuhksz
Version: 0.2.6
Summary: CUHK-SZ Weather MCP Server
Author-email: lkcy23 <lkcydream@gmail.com>
Maintainer-email: lkcy23 <lkcydream@gmail.com>
License: MIT License
Project-URL: Homepage, https://github.com/LKCY23/mcp-server-weather-cuhksz
Project-URL: Issues, https://github.com/LKCY23/mcp-server-weather-cuhksz/issues
Keywords: MCP,Weather
Requires-Python: >=3.10
License-File: LICENSE
Requires-Dist: httpx>=0.28.1
Requires-Dist: fastmcp>=2.0.0
Requires-Dist: python-dotenv
Requires-Dist: pydantic
Requires-Dist: PyJWT[crypto]
Dynamic: license-file
